lapras/__init__.py
lapras/detector.py
lapras/eda.py
lapras/main.py
lapras/merge.py
lapras/metrics.py
lapras/model.py
lapras/performance.py
lapras/plot.py
lapras/scorecard.py
lapras/selection.py
lapras/stats.py
lapras/transform.py
lapras/version.py
lapras/utils/__init__.py
lapras/utils/backwardSplit.py
lapras/utils/decorator.py
lapras/utils/forwardSplit.py
lapras/utils/func.py
lapras/utils/mapa.py
lapras/utils/mixin.py
lapras/utils/simpleMethods.py
lapras/utils/trendDiscretization.py
lapras/utils/trendSplit.py
lapras-0.0.23.data/data/README.md
lapras-0.0.23.dist-info/LICENSE
lapras-0.0.23.dist-info/METADATA
lapras-0.0.23.dist-info/WHEEL
lapras-0.0.23.dist-info/top_level.txt
lapras-0.0.23.dist-info/RECORD
