Metadata-Version: 2.1
Name: lapras
Version: 0.0.23
Summary: scorecard,logistical regression
Home-page: https://github.com/datasciencekun/lapras
Author: Hayden Yang
Author-email: yhangang@gmail.com
License: MIT
Keywords: scorecard,deep learning,data science,logistical regression
Classifier: Operating System :: POSIX
Classifier: Operating System :: Microsoft :: Windows
Classifier: Operating System :: MacOS :: MacOS X
Classifier: Programming Language :: Python :: 3.7
Classifier: Programming Language :: Python :: 3.8
Classifier: Programming Language :: Python :: 3.9
Requires-Python: >=3.7
License-File: LICENSE
